CHANGES.txt
MANIFEST.in
README.txt
buildout.cfg
setup.py
tox.ini
src/zc/__init__.py
src/zc.customdoctests.egg-info/PKG-INFO
src/zc.customdoctests.egg-info/SOURCES.txt
src/zc.customdoctests.egg-info/dependency_links.txt
src/zc.customdoctests.egg-info/namespace_packages.txt
src/zc.customdoctests.egg-info/not-zip-safe
src/zc.customdoctests.egg-info/requires.txt
src/zc.customdoctests.egg-info/top_level.txt
src/zc/customdoctests/README.txt
src/zc/customdoctests/__init__.py
src/zc/customdoctests/js.py
src/zc/customdoctests/spidermonkey.txt
src/zc/customdoctests/tests.py